bubble_api/__init__.py
bubble_api/client.py
bubble_api/constraint.py
bubble_api/field.py
bubble_api/asyncio/__init__.py
bubble_api/asyncio/client.py
bubble_api-0.5.1.dist-info/LICENSE
bubble_api-0.5.1.dist-info/METADATA
bubble_api-0.5.1.dist-info/WHEEL
bubble_api-0.5.1.dist-info/top_level.txt
bubble_api-0.5.1.dist-info/RECORD
