Metadata-Version: 2.1
Name: bubble-api
Version: 0.5.1
Summary: Interactions with Bubble.io API in Python made easy !
Author-email: Dylan NINA <settorac.nina@gmail.com>, Mathis Bourdin <mathisbrdn@gmail.com>
Project-URL: Homepage, https://github.com/settorac-nina/bubble-api
Project-URL: Bug Tracker, https://github.com/settorac-nina/bubble-api/issues
Classifier: Programming Language :: Python
Classifier: Programming Language :: Python :: 3
Classifier: Programming Language :: Python :: 3.8
Classifier: Programming Language :: Python :: 3.9
Classifier: Programming Language :: Python :: 3.10
Classifier: Programming Language :: Python :: 3.11
Classifier: License :: OSI Approved :: MIT License
Classifier: Operating System :: OS Independent
Requires-Python: >=3.8
License-File: LICENSE
Requires-Dist: requests
Requires-Dist: httpx
